keras2ncnn/__init__.py
keras2ncnn/__main__.py
keras2ncnn/graph_optimizer.py
keras2ncnn/graph_tool.py
keras2ncnn/h5df_parser.py
keras2ncnn/keras2ncnn.py
keras2ncnn/keras_converter.py
keras2ncnn/keras_debugger.py
keras2ncnn/ncnn_emitter.py
keras2ncnn/ncnn_param.py
keras2ncnn-0.2.0.dist-info/LICENSE
keras2ncnn-0.2.0.dist-info/METADATA
keras2ncnn-0.2.0.dist-info/WHEEL
keras2ncnn-0.2.0.dist-info/top_level.txt
keras2ncnn-0.2.0.dist-info/RECORD
