Metadata-Version: 2.1
Name: keras2ncnn
Version: 0.2.0
Summary: A keras h5df to ncnn converter
Home-page: https://github.com/MarsTechHAN/keras2ncnn
Author: Han Xiao
Author-email: hansh-sz@hotmail.com
License: UNKNOWN
Platform: UNKNOWN
Classifier: Programming Language :: Python :: 3
Classifier: License :: OSI Approved :: MIT License
Classifier: Operating System :: OS Independent
Requires-Python: >=3.5
License-File: LICENSE
Requires-Dist: h5py (>=2.10.0)
